pyselfi/__init__.py
pyselfi/likelihood.py
pyselfi/pool.py
pyselfi/posterior.py
pyselfi/selfi.py
pyselfi/utils.py
pyselfi/lotkavolterra/__init__.py
pyselfi/lotkavolterra/prior.py
pyselfi/lotkavolterra/selfi.py
pyselfi/power_spectrum/__init__.py
pyselfi/power_spectrum/prior.py
pyselfi/power_spectrum/selfi.py
pyselfi_examples/__init__.py
pyselfi_examples/grf/__init__.py
pyselfi_examples/grf/model/__init__.py
pyselfi_examples/grf/model/blackbox_GRF.py
pyselfi_examples/grf/model/setup_GRF.py
pyselfi_examples/lotkavolterra/model/__init__.py
pyselfi_examples/lotkavolterra/model/blackbox_LV.py
pyselfi_examples/lotkavolterra/model/setup_LV.py
pyselfi_examples/simbelmyne/__init__.py
pyselfi_examples/simbelmyne/model/__init__.py
pyselfi_examples/simbelmyne/model/blackbox_SBMY.py
pyselfi_examples/simbelmyne/model/setup_SBMY.py
pyselfi_examples/templates/new_blackbox.py
pyselfi_examples/templates/new_prior.py
pyselfi_examples/templates/new_selfi.py
pyselfi-2.0.dist-info/LICENSE
pyselfi-2.0.dist-info/METADATA
pyselfi-2.0.dist-info/WHEEL
pyselfi-2.0.dist-info/top_level.txt
pyselfi-2.0.dist-info/RECORD
