Metadata-Version: 2.1
Name: pyselfi
Version: 2.0
Summary: A python implementation of the Simulator Expansion for Likelihood-Free Inference (SELFI) algorithm
Author-email: Florent Leclercq <florent.leclercq@iap.fr>
License: GNU GENERAL PUBLIC LICENSE
Project-URL: Homepage, https://pyselfi.florent-leclercq.eu
Project-URL: Documentation, https://pyselfi.readthedocs.io/
Project-URL: Repository, https://github.com/florent-leclercq/pyselfi
Project-URL: Bug Tracker, https://github.com/florent-leclercq/pyselfi/issues
Classifier: Programming Language :: Python :: 3
Classifier: License :: OSI Approved :: GNU General Public License v3 or later (GPLv3+)
Classifier: Operating System :: OS Independent
Requires-Python: >=3.8
License-File: LICENSE
Requires-Dist: numpy
Requires-Dist: scipy
Requires-Dist: h5py
Requires-Dist: matplotlib
Requires-Dist: pathlib
Requires-Dist: scikit-learn
Provides-Extra: docs
Requires-Dist: docutils (==0.16) ; extra == 'docs'
Requires-Dist: breathe (==4.34.0) ; extra == 'docs'
Requires-Dist: jinja2 (==3.1.2) ; extra == 'docs'
Requires-Dist: sphinx (==5.0.2) ; extra == 'docs'
Requires-Dist: sphinx-rtd-theme (==0.4.3) ; extra == 'docs'
Requires-Dist: readthedocs-sphinx-ext ; extra == 'docs'
Provides-Extra: lotkavolterra_example
Requires-Dist: elfi (==0.8.3) ; extra == 'lotkavolterra_example'
Requires-Dist: lotkavolterra-simulator (==1.0) ; extra == 'lotkavolterra_example'
